pulse_cookie/__init__.py
pulse_cookie/_cli.py
pulse_cookie/_extractor.py
pulse_cookie-1.0.dist-info/LICENSE
pulse_cookie-1.0.dist-info/METADATA
pulse_cookie-1.0.dist-info/WHEEL
pulse_cookie-1.0.dist-info/entry_points.txt
pulse_cookie-1.0.dist-info/top_level.txt
pulse_cookie-1.0.dist-info/RECORD
