Metadata-Version: 2.1
Name: pulse-cookie
Version: 1.0
Summary: Minimal QtWebEngine-based Web UI to extract the Pulse Connect Secure authentication cookie for use with OpenConnect VPN
Author-email: Raj Magesh Gauthaman <raj.magesh@protonmail.com>
License: GNU GENERAL PUBLIC LICENSE
Project-URL: repository, https://codeberg.org/raj-magesh/pulse-cookie
Keywords: QtWebEngine,Pulse Connect Secure,OpenConnect,VPN,authentication,cookie
Classifier: Development Status :: 5 - Production/Stable
Classifier: License :: OSI Approved :: GNU General Public License v3 (GPLv3)
Classifier: Intended Audience :: End Users/Desktop
Classifier: Natural Language :: English
Classifier: Operating System :: POSIX :: Linux
Classifier: Programming Language :: Python :: 3
Classifier: Topic :: System :: Networking
Classifier: Typing :: Typed
Requires-Python: >=3.10
License-File: LICENSE
Requires-Dist: PyQt6-WebEngine
